ntucourse-0.1.1.dist-info/METADATA
ntucourse-0.1.1.dist-info/WHEEL
ntucourse-0.1.1.dist-info/entry_points.txt
ntucourse/__init__.py
ntucourse/__main__.py
ntucourse/client.py
ntucourse/config.py
ntucourse/model.py
ntucourse/new.py
ntucourse/old/__init__.py
ntucourse/old/base.py
ntucourse/old/course.py
ntucourse/old/label.py
ntucourse/old/main.py
ntucourse/old/params.py
ntucourse/old/search.py
ntucourse/old/utils.py
ntucourse/paginated_list.py
ntucourse/params.py
ntucourse/parse.py
ntucourse/prelude.py
ntucourse/query_sender.py
ntucourse/quick.py
ntucourse/search.py
ntucourse/utils.py
ntucourse-0.1.1.dist-info/RECORD
